{
	"alpha": {
		"version": "0.3.2",
		"url": "https://ivarptr.github.io/yu-writer.site/download.html"
	},
	
	"comment1": {
		"item": "lagacy before 0.3.1"
	},

	"beta": {
		"version": "0.4.5"
	},

	"comment2": {
		"item": "lagacy before 0.4.4"
	},

	"Pro": {
		"Beta" : {
			"version": "0.5.3"
		}
	},

	"comment3": {
		"item": "lagacy before 0.5.3"
	},

	"win32": {
		"Pro": {
			"Beta" : {
				"version": "0.5.3"
			}
		}
	},
	
	"darwin": {
		"Pro": {
			"Beta" : {
				"version": "0.5.3"
			}
		}
	},

	"linux": {
		"Pro": {
			"Beta" : {
				"version": "0.5.4"
			}
		}
	}
}